_dependencies/__init__.py
_dependencies/analyze.py
_dependencies/delegate.py
_dependencies/enclose.py
_dependencies/exceptions.py
_dependencies/graph.py
_dependencies/injectable.py
_dependencies/injector.py
_dependencies/lazy.py
_dependencies/objects/__init__.py
_dependencies/objects/attributes.py
_dependencies/objects/classes.py
_dependencies/objects/data.py
_dependencies/objects/descriptor.py
_dependencies/objects/enum.py
_dependencies/objects/nested.py
_dependencies/objects/package.py
_dependencies/objects/shield.py
_dependencies/objects/this.py
_dependencies/objects/value.py
_dependencies/resolve.py
_dependencies/scope.py
_dependencies/spec.py
_dependencies/stack.py
_dependencies/state.py
_dependencies/trace.py
dependencies/__init__.py
dependencies/exceptions.py
dependencies-7.6.0.dist-info/LICENSE
dependencies-7.6.0.dist-info/WHEEL
dependencies-7.6.0.dist-info/METADATA
dependencies-7.6.0.dist-info/RECORD
